ATTRIBUTIONS
CHANGELOG.rst
LICENCE
MANIFEST.in
README.rst
setup.py
py_toolbox.egg-info/PKG-INFO
py_toolbox.egg-info/SOURCES.txt
py_toolbox.egg-info/dependency_links.txt
py_toolbox.egg-info/entry_points.txt
py_toolbox.egg-info/top_level.txt
pytb/__init__.py
pytb/__main__.py
pytb/config.py
pytb/core.py
pytb/importlib.py
pytb/io.py
pytb/itertools.py
pytb/notification.py
pytb/rdb.py
pytb/schedule.py
pytb/test/test_config.py
pytb/test/test_importlib.py
pytb/test/test_io.py
pytb/test/test_itertools.py
pytb/test/test_notification.py
pytb/test/test_schedule.py