Metadata-Version: 2.1
Name: py-toolbox
Version: 0.7.0
Summary: A collection of commonly used python snippets
Home-page: https://github.com/dangrie158/py-toolbox
Author: Daniel Grießhaber
Author-email: dangrie158@gmail.com
License: MIT
Platform: UNKNOWN
Classifier: Development Status :: 1 - Planning
Classifier: Topic :: Utilities
Classifier: License :: OSI Approved :: MIT License
